 <launch>
  <arg name="scan_topic"  default="scan" />
  <arg name="base_frame"  default="base_footprint"/>
  <arg name="odom_frame"  default="odom"/>

  <node pkg="semantic_mapping_v2" type="semantic_mapping" name="semantic_mapping" output="screen" launch-prefix="xterm -sl 10000 -hold -e" >
    <param name="gmapping/base_frame" value="$(arg base_frame)"/>
    <param name="gmapping/odom_frame" value="$(arg odom_frame)"/>
    <param name="gmapping/map_update_interval" value="5.0"/>
    <param name="gmapping/maxUrange" value="3.5"/>
    <param name="gmapping/maxRange" value="4.5"/>
    <param name="gmapping/sigma" value="0.05"/>
    <param name="gmapping/kernelSize" value="1"/>
    <param name="gmapping/lstep" value="0.05"/>
    <param name="gmapping/astep" value="0.05"/>
    <param name="gmapping/iterations" value="5"/>
    <param name="gmapping/lsigma" value="0.01"/>
    <param name="gmapping/ogain" value="3.0"/>
    <param name="gmapping/lskip" value="0"/>
    <param name="gmapping/minimumScore" value="200"/>
    <param name="gmapping/srr" value="0.01"/>
    <param name="gmapping/srt" value="0.02"/>
    <param name="gmapping/str" value="0.01"/>
    <param name="gmapping/stt" value="0.02"/>
    <param name="gmapping/linearUpdate" value="0.5"/>
    <param name="gmapping/angularUpdate" value="0.436"/>
    <param name="gmapping/temporalUpdate" value="-1.0"/>
    <param name="gmapping/resampleThreshold" value="0.5"/>
    <param name="gmapping/particles" value="10"/>

    <param name="gmapping/xmin" value="-1.0"/>
    <param name="gmapping/ymin" value="-1.0"/>
    <param name="gmapping/xmax" value="1.0"/>
    <param name="gmapping/ymax" value="1.0"/>

    <param name="gmapping/delta" value="0.05"/>
    <param name="gmapping/llsamplerange" value="0.01"/>
    <param name="gmapping/llsamplestep" value="0.01"/>
    <param name="gmapping/lasamplerange" value="0.005"/>
    <param name="gmapping/lasamplestep" value="0.005"/>
    <remap from="scan" to="$(arg scan_topic)"/>

    <param name="Octomap/resolution" value="0.125" />    
    <param name="Octomap/frame_id" type="string" value="map" />                 <!-- fixed map frame (set to 'map' if SLAM or localization running!) -->    
    <param name="Octomap/sensor_model/max_range" value="4.0" />                 <!-- maximum range to integrate (speedup!) -->    
    <param name="Octomap/pointcloud_min_z" value="0.25" />                       <!-- maximum range to integrate (speedup!) -->    
    <param name="Octomap/pointcloud_max_z" value="1.8" />                       <!-- maximum range to integrate (speedup!) -->    
    <param name="Octomap/sensor_model/hit" value="0.65" />                       <!-- maximum range to integrate (speedup!) -->    
    <param name="Octomap/sensor_model/miss" value="0.4" />                       <!-- maximum range to integrate (speedup!) -->    
    <param name="Octomap/occupancy_thresh" value="0.5" />
    <param name="Octomap/downproject_occ_thresh" value="0.6" />
    <param name="Octomap/downproject_dilate_iters" value="2" />
    <param name="Octomap/downproject_erode_iters" value="4" />
    <param name="Octomap/downsample_voxel_size" value="0.03" />                       <!-- maximum range to integrate (speedup!) --> 

    <param name="RoomTypeMapper/CELL_HIT_MISS_RATIO" value="4.0" /> 
    <param name="RoomTypeMapper/ROOM_HIT_MISS_RATIO" value="1.2" />                
    <param name="RoomTypeMapper/ROOM_MIN_PROB" value="0.0005" />
    <param name="RoomTypeMapper/ROOM_DEFAULT_RESOLUTION" value="2.0" />
    <param name="RoomTypeMapper/ASUS_FOV" value="29" />
    <param name="RoomTypeMapper/MIN_DIST" value="0.5" />
    <param name="RoomTypeMapper/MAX_DIST" value="4.0" />  

    <param name="ObjectMapper/OBJ_PRIOR_PROB" value="0.01" />  
    <param name="ObjectMapper/OBJ_MIN_PROB" value="0.0001" />  
    <param name="ObjectMapper/OBJ_MAX_PROB" value="0.9" />  
    <param name="ObjectMapper/OBJ_DEFAULT_RESOLUTION" value="4.0" />  
    <param name="ObjectMapper/OBJ_DEFUALT_MAX_HEIGHT" value="1.6" />  
    <param name="ObjectMapper/V_H" value="0.3" />   
    <param name="ObjectMapper/V_M" value="0.0002" />  
    <param name="ObjectMapper/OBJ_NAME_FILE" value="/home/thomas/darknet/data/coco.names" />  

  </node>
</launch>
